LICENSE
MANIFEST.in
README.rst
setup.py
atrip/__init__.py
atrip/_metadata.py
atrip/_version.py
atrip/archiver.py
atrip/cartridge.py
atrip/char_mapping.py
atrip/collection.py
atrip/compressor.py
atrip/container.py
atrip/errors.py
atrip/executables.py
atrip/file_type.py
atrip/filesystem.py
atrip/magic.py
atrip/mame.py
atrip/media_type.py
atrip/omnivore_loader.py
atrip/segment.py
atrip/signature.py
atrip/standard_delivery.py
atrip/stringifier.py
atrip/style_bits.py
atrip/utils.py
atrip.egg-info/PKG-INFO
atrip.egg-info/SOURCES.txt
atrip.egg-info/dependency_links.txt
atrip.egg-info/entry_points.txt
atrip.egg-info/requires.txt
atrip.egg-info/top_level.txt
atrip/archivers/__init__.py
atrip/archivers/tar.py
atrip/archivers/zip.py
atrip/compressors/__init__.py
atrip/compressors/bzip.py
atrip/compressors/dcm.py
atrip/compressors/gzip.py
atrip/compressors/lz4.py
atrip/compressors/lzma.py
atrip/compressors/unix_compress.py
atrip/compressors/zlib.py
atrip/file_types/__init__.py
atrip/file_types/atari_xex.py
atrip/filesystems/__init__.py
atrip/filesystems/apple_dos33.py
atrip/filesystems/atari_cas.py
atrip/filesystems/atari_dos2.py
atrip/filesystems/atari_jumpman.py
atrip/filesystems/dummy.py
atrip/filesystems/fstbt.py
atrip/filesystems/kboot.py
atrip/filesystems/mydos.py
atrip/filesystems/spartados.py
atrip/machines/__init__.py
atrip/machines/atari8bit/__init__.py
atrip/machines/atari8bit/jumpman/__init__.py
atrip/machines/atari8bit/jumpman/parser.py
atrip/machines/atari8bit/jumpman/playfield.py
atrip/media_types/__init__.py
atrip/media_types/apple_disks.py
atrip/media_types/atari_carts.py
atrip/media_types/atari_disks.py
atrip/media_types/atari_tapes.py
atrip/signatures/__init__.py
atrip/signatures/atari2600_cart.py
atrip/signatures/atari2600_starpath.py
atrip/signatures/atari5200_cart.py
atrip/signatures/vectrex.py
atrip/templates/dos2dd.atr
atrip/templates/dos2dd.atr.inf
atrip/templates/dos2ed+2.5.atr
atrip/templates/dos2ed+2.5.atr.inf
atrip/templates/dos2ed.atr
atrip/templates/dos2ed.atr.inf
atrip/templates/dos2sd+2.0s.atr
atrip/templates/dos2sd+2.0s.atr.inf
atrip/templates/dos2sd.atr
atrip/templates/dos2sd.atr.inf
atrip/templates/dos33.dsk
