Metadata-Version: 1.2
Name: atrip
Version: 0.5.0
Summary: Utility to manage file systems on retro computer disk images
Home-page: https://github.com/robmcmullen/atrip
Author: Rob McMullen
Author-email: feedback@playermissile.com
License: GPL
Platform: UNKNOWN
Classifier: Programming Language :: Python :: 3.6
Classifier: Intended Audience :: Developers
Classifier: License :: OSI Approved :: GNU General Public License (GPL)
Classifier: Topic :: Software Development :: Libraries
Classifier: Topic :: Utilities
Requires-Python: >=3.6
